[
  {
    "pageContent": "<path>Type Alias: CrosspostOptions, Type declaration, subredditName</path>\n[**@devvit/public-api v0.12.0-dev**](../../README.md)\n# Type Alias: CrosspostOptions\n**CrosspostOptions** = [`CommonSubmitPostOptions`](CommonSubmitPostOptions.md) & `object`\n## Type declaration\n### postId\n**postId**: `string`\n### subredditName\n**subredditName**: `string`",
    "metadata": {
      "type": [
        "text",
        "heading"
      ],
      "path": [
        "Type Alias: CrosspostOptions",
        "Type declaration",
        "subredditName"
      ],
      "level": 0
    }
  }
]