[
  {
    "pageContent": "<path>Enumeration: UserContext, Enumeration Members, MODERATOR</path>\n# Enumeration: UserContext\n## Table of contents\n### Enumeration Members\n-   [LOGGED\\_OUT](UserContext.md#logged_out)\n-   [MEMBER](UserContext.md#member)\n-   [MODERATOR](UserContext.md#moderator)\n## Enumeration Members\n### LOGGED_OUT\n• **LOGGED\\_OUT** = `\"loggedOut\"`\n### MEMBER\n• **MEMBER** = `\"member\"`\n### MODERATOR\n• **MODERATOR** = `\"moderator\"`",
    "metadata": {
      "type": [
        "heading",
        "text"
      ],
      "path": [
        "Enumeration: UserContext",
        "Enumeration Members",
        "MODERATOR"
      ],
      "level": 1
    }
  }
]